pikachu/__init__.py
pikachu/errors.py
pikachu/general.py
pikachu/math_functions.py
pikachu/chem/__init__.py
pikachu/chem/aromatic_system.py
pikachu/chem/atom.py
pikachu/chem/atom_properties.py
pikachu/chem/bond.py
pikachu/chem/bond_properties.py
pikachu/chem/chirality.py
pikachu/chem/electron.py
pikachu/chem/kekulisation.py
pikachu/chem/lone_pair.py
pikachu/chem/orbital.py
pikachu/chem/shell.py
pikachu/chem/structure.py
pikachu/chem/substructure.py
pikachu/chem/substructure_matching.py
pikachu/chem/molfile/__init__.py
pikachu/chem/molfile/read_molfile.py
pikachu/chem/molfile/write_molfile.py
pikachu/chem/rings/__init__.py
pikachu/chem/rings/find_cycles.py
pikachu/chem/rings/ring_identification.py
pikachu/drawing/__init__.py
pikachu/drawing/colours.py
pikachu/drawing/drawing.py
pikachu/drawing/rings.py
pikachu/drawing/sssr.py
pikachu/fingerprinting/__init__.py
pikachu/fingerprinting/daylight.py
pikachu/fingerprinting/ecfp_4.py
pikachu/fingerprinting/hashing.py
pikachu/fingerprinting/map_4.py
pikachu/fingerprinting/similarity.py
pikachu/inchi/__init__.py
pikachu/inchi/inchi.py
pikachu/parsers/__init__.py
pikachu/parsers/coconut.py
pikachu/parsers/np_atlas.py
pikachu/reactions/__init__.py
pikachu/reactions/basic_reactions.py
pikachu/reactions/functional_groups.py
pikachu/smiles/__init__.py
pikachu/smiles/graph_to_smiles.py
pikachu/smiles/smiles.py
pikachu_chem-1.1.4.dist-info/licenses/LICENSE.txt
tests/__init__.py
tests/test_graph_to_smiles.py
tests/test_orbital.py
tests/test_structure.py
tests/test_substructure_matching.py
tests/test_data/__init__.py
pikachu_chem-1.1.4.dist-info/METADATA
pikachu_chem-1.1.4.dist-info/WHEEL
pikachu_chem-1.1.4.dist-info/top_level.txt
pikachu_chem-1.1.4.dist-info/RECORD
