Metadata-Version: 2.4
Name: pikachu-chem
Version: 1.1.4
Summary: PIKACHU: Python-based Informatics Kit for Analysing CHemical Units
Author: Barbara Terlouw
Author-email: barbara.terlouw@wur.nl
License-File: LICENSE.txt
Requires-Dist: matplotlib
Dynamic: author
Dynamic: author-email
Dynamic: description
Dynamic: license-file
Dynamic: requires-dist
Dynamic: summary
